<?xml version="1.0" encoding="UTF-8" standalone="yes"?>
<deviceDataDataSet>
  <basalDataLog/>
  <bgReadingDataLog>
    <bgReading active="true" clockOff="false"
      deviceSerialNumber="XXXXXXXX" deviceType="METERTYPES_ONETOUCHVERIOREFLECT" edited="false"
      futureDated="false" imported="false"
      manual="false" readingDate="2020-10-14T19:12:11">
      <bgValue units="mg/dL">159</bgValue>
      <cgmCalibration>false</cgmCalibration>
      <mealTag>MEAL_TAG_POST_MEAL</mealTag>
    </bgReading>
  </bgReadingDataLog>
  <bolusDataLog>
    <bolus active="true" deviceSerialNumber="XXXXXXXX"
      deviceType="METERTYPES_ONETOUCHVERIOREFLECT" entryType="ENTRY_TYPE_BOLUS" imported="true"
      mixedDated="false"
      omitted="false" readingDate="2020-10-29T22:42:16">
      <bgCorrection>false</bgCorrection>
      <bolusDelivered units="U">10</bolusDelivered>
      <injectedInsulinType>NON_BOLUS_INSULIN_LONG</injectedInsulinType>
      <mealCorrection>false</mealCorrection>
    </bolus>
  </bolusDataLog>
  <cgmDataLog/>
  <description>Data Set for Trident Training [ttc.patient20]</description>
  <deviceEventDataLog/>
  <deviceSettingsDataLog/>
  <foodDataLog>
    <food active="true" clockOff="false"
      deviceSerialNumber="XXXXXXXX" deviceType="METERTYPES_ONETOUCHVERIOREFLECT" editable="false"
      edited="false" futureDated="false"
      imported="true" manual="false" mixedDated="false" omitted="false"
      readingDate="2020-11-02T10:30:32">
      <annotation>
        <active>true</active>
        <annotation>Oatmeal with apple and walnuts</annotation>
        <patientEntered>true</patientEntered>
      </annotation>
      <carbohydrates units="g">50</carbohydrates>
      <extendedAttributes>
        <attributeValue name="dataLogs_ordinal" type="string">0</attributeValue>
      </extendedAttributes>
      <mealSize>MEAL_SIZE_LARGE</mealSize>
    </food>
  </foodDataLog>
  <healthAttribsDataLog>
    <healthAttrib active="true" clockOff="false"
      deviceSerialNumber="XXXXXXXX" deviceType="METERTYPES_ONETOUCHVERIOREFLECT" editable="true"
      edited="false" futureDated="false"
      imported="true" manual="false" mixedDated="false" omitted="false"
      readingDate="2020-10-31T14:40:00">
      <annotation>
        <active>true</active>
        <annotation>Lunch hour walk</annotation>
        <patientEntered>true</patientEntered>
      </annotation>
      <extendedAttributes>
        <attributeValue name="dataLogs_healthAttributes_excersizeIntensity" type="string">
          EXERCISE_INTENSITY_MILD
        </attributeValue>
      </extendedAttributes>
      <healthAtributesLookup>HEALTH_ATTRIBUTE_EXERCISE</healthAtributesLookup>
      <healthAttributesValue>20</healthAttributesValue>
    </healthAttrib>
  </healthAttribsDataLog>
  <tddDataLog/>
</deviceDataDataSet>
